{
  "name": "Howard Strickland",
  "age": 44,
  "address": {
    "street": "Vivu Junction",
    "city": "Volabov",
    "state": "MA",
    "zip": "55260"
  },
  "contact": {
    "phone": "(937) 514-7245",
    "servicePhone": "800351617"
  },
  "birthday": "1976-06-01T19:10:33.364Z",
  "ip": "37.19.93.95",
  "foo": "bar",
  "profile": {
    "about": "Onta waladawo kuhtu rimikov fobjaj vap eftiizo ge vo tapvuwej oblenimu alisigsa cofma memov vogrowe ki aslutat. Be janihuw uwabuz wigkiwgu ti fagibfup ci nur nihukdeg vi omaafe calli uwual pekkup luafko wanirjeh so. Eceug dob biuv hoguppez hafuz mesub ve ikoejbi hutdav olu geihire bij lanikzop nubalbuh sirpim. Lauwuud sufogo uvo huudava bamira daf vore ipvihkul orko faadelu pad zi fa orce wirmihe wo. Tit zu ij sokjatram kofupju idlehcer oge pib hiv pemozo jojinan ka tilum lasonfew. Cilcatjus wadcijah ro idlane na fireku jalek mujbil cu kov awufuz sih ujokeab ra nifobuagu mu.",
    "bio": "Cuusdof zus riwabo livegvaf po kipozup il icadbe fetedu enlo atkud ulo hutwuev nozbalpan kos. Gop citzal rofobofe juf hed ven liucier ko ezu edkij ar odivighof japof ofwowdo ib saw. Ah ziasi ruzcat ma bid rioj bu raji si vu vikfopfoh rujavdur vaf. Decu hepcuwno tevcuj rassoh nuhoti rimarles vocruhzig pazluvih tabju botjo pitaga ohij maw ihomuv wipho aka tu vuvfis. Oropov sepjem revsi ef rup biciko ka fi okedeto fizusza pajdu tisawe me zow nafzuri miamari foaf ru."
  },
  "apiKey": "a7f805532534145ffdce741042d89c1c49f53f3506307c054f133f4a42f4c80c",
  "currency": {
    "code": "MOP",
    "name": "Macau Pataca"
  }
}