{
  "name": "Claudia Baker",
  "age": 46,
  "address": {
    "street": "Osinap Key",
    "city": "Umetudcoz",
    "state": "WV",
    "zip": "24835"
  },
  "contact": {
    "phone": "(335) 295-9797",
    "servicePhone": "800856378"
  },
  "birthday": "1969-10-28T06:41:55.212Z",
  "ip": "181.22.232.245",
  "foo": "bar",
  "profile": {
    "about": "Fiwol fesawdiw cidukamo magvub murrizat hurotuz detsug rufhub saggafofo eluze car juw wis jo lon. Ziupohi pupwu sede kephicuh le bopatmuh kuz vibmen abbe ojicugew bitajula zebni mibtuk ewusiedi. Gemezeg ruhgo kuhzug di neeliz fam bu gehni sugimre ik udubev efril ol. Ukobejo kuvni ginziram kajac asna apejoow ketbelfu odauw ke mu kahe wag bipocak ut dim. Woajifoc be ep wo ci ju pejef edeziv je zapkuwe woneb ber mubunhi ophap urusussa nahofluj. Za sudtipi zicsovcap una ew la onserfoz ukiper risibfev arobber ragsitew loenu eg ri hawwi. Fakjudfen ge luz fez nin gu ba teg sutehejin kumij suanpan fuujobi sop egovuzig.",
    "bio": "Hofruz lunlussur ecokizcu cana pe huhe hotoow vewdohkug ejike ar idcanpar ip dizip fe. Ul boh tu tog ud rofiz aniviniv co zutar duwujho vaj se. Ruacsus leta ro sicdu socpu map cafwaesi awogej fabma wap wi tokuj od keshi siju rodepju olpoari. Diz usmu bo ulofawrib jezepu gu wuz cuk birre tefejham ju ugpud rabelca. Nuene nacuririb kulil naz kage vukusob vuvurlek irra hulko gadu lotomhu bujek jiv. Anlub ro kesahlaw kijij hujzuduz nelcektom oku romaseid jin ralezivo odevugvop sisbehu mus."
  },
  "apiKey": "2efc09723228878cac8461bbb1b5f3fb33ab234a8c7166619bc217ea799dae3f",
  "currency": {
    "code": "SGD",
    "name": "Singapore Dollar"
  }
}